tf_lessons/__init__.py
tf_lessons/lesson_1.py
tf_lessons-0.1.2.dist-info/LICENSE
tf_lessons-0.1.2.dist-info/WHEEL
tf_lessons-0.1.2.dist-info/METADATA
tf_lessons-0.1.2.dist-info/RECORD
