Metadata-Version: 2.1
Name: tf_lessons
Version: 0.1.2
Summary: An amazing sample package!
Home-page: https://github.com/nepito/tf_lessons
Author: Ciencia de Datos • GECI
Author-email: ciencia.datos@islas.org.mx
Requires-Python: >=3.9
Classifier: License :: OSI Approved :: GNU General Public License v3 or later (GPLv3+)
Requires-Dist: numpy
Requires-Dist: tensorflow
